LICENSE
MANIFEST.in
README.rst
setup.py
persistent/__init__.py
persistent/database.py
persistent/errors.py
persistent/persistent.py
persistent/query.py
python_object_persistence.egg-info/PKG-INFO
python_object_persistence.egg-info/SOURCES.txt
python_object_persistence.egg-info/dependency_links.txt
python_object_persistence.egg-info/top_level.txt