Metadata-Version: 1.0
Name: python-object-persistence
Version: 0.9.3
Summary: Easily save, load, query your Python objects with SQLite3.
Home-page: https://github.com/fictorial/python-object-persistence
Author: Brian Hammond
Author-email: brian@fictorial.com
License: The MIT License (MIT)
